<canvas>
	<level id='1' x='2220' y='680'>
		<line>w - - - - - - b -</line>
		<line>- w - - r - - w -</line>
		<line>- - - r - - - - w</line>
		<line>- - - - b - - b -</line>
		<line>- - - w b - - w -</line>
		<line>w w - - w - - w -</line>
		<line>- w - - - - - - -</line>
		<line>- - - w - - - b -</line>
		<line>- b - - w - g - -</line>
	</level>
	<level id='2' x='400' y='80'>
		<line>w - - - w - - b -</line>
		<line>- w - - - - - w -</line>
		<line>- - - w - - - w -</line>
		<line>- - - - w - - b -</line>
		<line>- - - w - - - w -</line>
		<line>w w - - w - - w -</line>
		<line>- w - - - - - - -</line>
		<line>- - - w - - - b -</line>
		<line>- b - - w - p - -</line>
	</level>

</canvas>